magi_cli/__init__.py
magi_cli/cast.py
magi_cli/artifacts/__init__.py
magi_cli/loci/__init__.py
magi_cli/loci/spellcraft/__init__.py
magi_cli/loci/spellcraft/sigildry.py
magi_cli/loci/spellcraft/spell_builder.py
magi_cli/loci/spellcraft/spell_bundle.py
magi_cli/loci/spellcraft/spell_parse.py
magi_cli/spells/__init__.py
magi_cli/spells/banish.py
magi_cli/spells/divine.py
magi_cli/spells/fireball.py
magi_cli/spells/necromancy.py
magi_cli/spells/ponder.py
magi_cli/spells/raise_dead.py
magi_cli/spells/spellcraft.py
magi_cli_pypi-1.0.3.dist-info/METADATA
magi_cli_pypi-1.0.3.dist-info/WHEEL
magi_cli_pypi-1.0.3.dist-info/entry_points.txt
magi_cli_pypi-1.0.3.dist-info/top_level.txt
magi_cli_pypi-1.0.3.dist-info/RECORD
