Metadata-Version: 2.4
Name: magi_cli_pypi
Version: 1.0.3
Summary: Magi_CLI is a command line interface for those who desire software development to feel more like magic.
Home-page: https://github.com/bobbyhiddn/Magi_CLI
Author: Micah Longmire
Author-email: mlmicahlongmire@gmail.com
Classifier: Programming Language :: Python :: 3
Classifier: License :: OSI Approved :: MIT License
Classifier: Operating System :: OS Independent
Requires-Python: >=3.9
Requires-Dist: Click
Requires-Dist: requests
Requires-Dist: setuptools
Requires-Dist: svgwrite
Dynamic: author
Dynamic: author-email
Dynamic: classifier
Dynamic: description
Dynamic: description-content-type
Dynamic: home-page
Dynamic: requires-dist
Dynamic: requires-python
Dynamic: summary
